shittycorn/__init__.py
shittycorn/__main__.py
shittycorn-0.0.11.dist-info/METADATA
shittycorn-0.0.11.dist-info/WHEEL
shittycorn-0.0.11.dist-info/top_level.txt
shittycorn-0.0.11.dist-info/RECORD
