Metadata-Version: 2.1
Name: shittycorn
Version: 0.0.11
Summary: a shitty web server
